rdp_quick/__init__.py
rdp_quick/check_window.py
rdp_quick/compute_distance.py
rdp_quick/curvature.py
rdp_quick-1.0.3.dist-info/LICENSE
rdp_quick-1.0.3.dist-info/METADATA
rdp_quick-1.0.3.dist-info/WHEEL
rdp_quick-1.0.3.dist-info/top_level.txt
rdp_quick-1.0.3.dist-info/RECORD
