Metadata-Version: 2.1
Name: rdp-quick
Version: 1.0.3
Summary: fast implementation of Ramer-Douglas-Peucker
Home-page: https://github.com/DrJohnDale/rdp-quick
Author: Dr John Dale
License: MIT
Classifier: Programming Language :: Python :: 3
Classifier: License :: OSI Approved :: MIT License
Classifier: Operating System :: OS Independent
License-File: LICENSE
Requires-Dist: numpy
Requires-Dist: numba
Requires-Dist: scipy
